productivity_timer/__init__.py
productivity_timer/py.typed
productivity_timer/timer.py
productivity_timer-1.0.2.dist-info/LICENSE
productivity_timer-1.0.2.dist-info/METADATA
productivity_timer-1.0.2.dist-info/WHEEL
productivity_timer-1.0.2.dist-info/top_level.txt
productivity_timer-1.0.2.dist-info/RECORD
