Metadata-Version: 2.1
Name: productivity-timer
Version: 1.0.2
Summary: A timer library for managing multiple timers for multiple individuals.
Home-page: https://github.com/Abhi-shekes/productivity-timer
Author: Abhishek
Author-email: abhishekshivtiwari@gmail.com
Classifier: Programming Language :: Python :: 3
Classifier: License :: OSI Approved :: MIT License
Classifier: Operating System :: OS Independent
Requires-Python: >=3.6
License-File: LICENSE
